plot_confusion_matrix/__init__.py
plot_confusion_matrix/confusion_matrix.py
plot_confusion_matrix-0.0.1.dist-info/METADATA
plot_confusion_matrix-0.0.1.dist-info/WHEEL
plot_confusion_matrix-0.0.1.dist-info/licenses/LICENSE
plot_confusion_matrix-0.0.1.dist-info/RECORD
